ionntxpred/python_scripts/__init__.py
ionntxpred/python_scripts/ionntxpred.py
ionntxpred/python_scripts/BLAST/ca_all_db/ca_train.pdb
ionntxpred/python_scripts/BLAST/ca_all_db/ca_train.phr
ionntxpred/python_scripts/BLAST/ca_all_db/ca_train.pin
ionntxpred/python_scripts/BLAST/ca_all_db/ca_train.pjs
ionntxpred/python_scripts/BLAST/ca_all_db/ca_train.pog
ionntxpred/python_scripts/BLAST/ca_all_db/ca_train.pos
ionntxpred/python_scripts/BLAST/ca_all_db/ca_train.pot
ionntxpred/python_scripts/BLAST/ca_all_db/ca_train.psq
ionntxpred/python_scripts/BLAST/ca_all_db/ca_train.ptf
ionntxpred/python_scripts/BLAST/ca_all_db/ca_train.pto
ionntxpred/python_scripts/BLAST/k_all_db/k_train.pdb
ionntxpred/python_scripts/BLAST/k_all_db/k_train.phr
ionntxpred/python_scripts/BLAST/k_all_db/k_train.pin
ionntxpred/python_scripts/BLAST/k_all_db/k_train.pjs
ionntxpred/python_scripts/BLAST/k_all_db/k_train.pog
ionntxpred/python_scripts/BLAST/k_all_db/k_train.pos
ionntxpred/python_scripts/BLAST/k_all_db/k_train.pot
ionntxpred/python_scripts/BLAST/k_all_db/k_train.psq
ionntxpred/python_scripts/BLAST/k_all_db/k_train.ptf
ionntxpred/python_scripts/BLAST/k_all_db/k_train.pto
ionntxpred/python_scripts/BLAST/na_all_db/na_train.pdb
ionntxpred/python_scripts/BLAST/na_all_db/na_train.phr
ionntxpred/python_scripts/BLAST/na_all_db/na_train.pin
ionntxpred/python_scripts/BLAST/na_all_db/na_train.pjs
ionntxpred/python_scripts/BLAST/na_all_db/na_train.pog
ionntxpred/python_scripts/BLAST/na_all_db/na_train.pos
ionntxpred/python_scripts/BLAST/na_all_db/na_train.pot
ionntxpred/python_scripts/BLAST/na_all_db/na_train.psq
ionntxpred/python_scripts/BLAST/na_all_db/na_train.ptf
ionntxpred/python_scripts/BLAST/na_all_db/na_train.pto
ionntxpred/python_scripts/BLAST/other_all_db/other_train.pdb
ionntxpred/python_scripts/BLAST/other_all_db/other_train.phr
ionntxpred/python_scripts/BLAST/other_all_db/other_train.pin
ionntxpred/python_scripts/BLAST/other_all_db/other_train.pjs
ionntxpred-1.2.dist-info/LICENSE.txt
ionntxpred-1.2.dist-info/METADATA
ionntxpred-1.2.dist-info/WHEEL
ionntxpred-1.2.dist-info/entry_points.txt
ionntxpred-1.2.dist-info/top_level.txt
ionntxpred-1.2.dist-info/RECORD
