Metadata-Version: 2.2
Name: ionntxpred
Version: 1.2
Summary: IonNTxPred: Prediction and design of ion channel-impairing proteins using protein language models.
Home-page: https://github.com/raghavagps/IonNTxPred
Author: Anand Singh Rathore
Author-email: anandr@iiitd.ac.in, anandrathoreindia@gmail.com
License: GPL-3.0
Classifier: Programming Language :: Python :: 3
Classifier: License :: OSI Approved :: GNU General Public License v3 (GPLv3)
Classifier: Operating System :: OS Independent
Classifier: Intended Audience :: Science/Research
Classifier: Topic :: Scientific/Engineering :: Bio-Informatics
Requires-Python: >=3.9
License-File: LICENSE.txt
Dynamic: author
Dynamic: author-email
Dynamic: classifier
Dynamic: description
Dynamic: description-content-type
Dynamic: home-page
Dynamic: license
Dynamic: requires-python
Dynamic: summary
